{
  "name": "John Joseph O'Connor",
  "url": "http://jewornotjew.com/profile.jsp?ID=1944",
  "verdict": "Barely a Jew",
  "description": "When we were children and engrossed ourselves in \"The Three Musketeers\", we learned to hate The Cardinal. (Richelieu, natch, but for every musketeer fan, he will always simply be \"The Cardinal\".) The Cardinal was pure evil.\n\nEver since, when we saw cardinals mentioned in real life, we couldn't help but be a tad wary. Perhaps because they are powerful Catholic figures, and we are Jews. Not exactly a historically friendly combination.\n\nBut then, we found about Cardinal O'Connor of New York. He was quite... a mensch. Outspoken opponent of antisemitism, defender of Holocaust victims, Jew. Yes, you heard that right, Jew.\n\nWell, sort of. O'Connor's mother was born Jewish, but converted and hid it from her family. So it's possible that the cardinal wasn't even aware of his partial Jewishness.\n\nWe guess not all cardinals are pure evil...",
  "pros": null,
  "cons": null,
  "score": 1944,
  "category": "",
  "image_url": "http://jewornotjew.com/img/people/j/john_joseph_oconnor.jpg",
  "created_at": "2025-03-29T13:17:12+02:00",
  "updated_at": "2025-03-29T13:17:12+02:00"
}